Metadata-Version: 2.1
Name: convolvecl
Version: 2022.5.10
Summary: convolution of angular power spectra
Home-page: https://github.com/cltools/convolvecl
Maintainer: Nicolas Tessore
Maintainer-email: n.tessore@ucl.ac.uk
License: MIT
Project-URL: Documentation, https://cltools.readthedocs.io/gaussiancl/
Platform: UNKNOWN
Classifier: Programming Language :: Python :: 3
Classifier: License :: OSI Approved :: MIT License
Classifier: Operating System :: OS Independent
Requires-Python: >=3.6
